[{"mb_no":"51","mb_id":"luffy7","mb_password":"*015EC1447D05EEC6144D2AE392D55B262FAC2547","mb_name":"구리구리","mb_nick":"구리구리","mb_nick_date":"2016-08-17","mb_email":"ruffy15@gmail.com","mb_homepage":"","mb_level":"3","mb_sex":"","mb_birth":"","mb_tel":"(+82)92029292","mb_hp":"(+81)01029292929","mb_certify":"","mb_adult":"0","mb_dupinfo":"","mb_zip1":"","mb_zip2":"","mb_addr1":"","mb_addr2":"","mb_addr3":"","mb_addr_jibeon":"","mb_signature":"","mb_recommend":"","mb_point":"0","mb_today_login":"2016-08-26 09:43:39","mb_login_ip":"1.217.54.28","mb_datetime":"2016-08-17 17:17:31","mb_ip":"1.217.54.28","mb_leave_date":"","mb_intercept_date":"","mb_email_certify":"2016-08-17 17:32:44","mb_email_certify2":"","mb_memo":"","mb_lost_certify":"","mb_mailling":"1","mb_sms":"0","mb_open":"0","mb_open_date":"2016-08-17","mb_profile":"","mb_memo_call":"","mb_1":"8JQH-OF5Y-148B-0KLF","mb_2":"slsl","mb_3":"(+82)1012923838","mb_4":"C-1","mb_5":"뷰티종합","mb_6":"kkkk","mb_7":"2016-08-19 14:41:28","mb_8":"FAIL","mb_9":"","mb_10":"3","mb_11":"","mb_12":"뷰티종합 컨설팅지도사","mb_13":"22","mb_14":"뷰티종합컨설팅지도사 C-2 Class","mb_15":"2016-08-18 15:45:57","mb_16":""}]